{"is_source_file": true, "format": "Python", "description": "This file generates and saves the OpenAPI schema for a FastAPI application. It retrieves the schema from the app instance, then writes it to a JSON file in the 'interfaces' directory.", "external_files": ["src/api/main.py"], "external_methods": ["src.api.main.app.openapi"], "published": [], "classes": [], "methods": [{"name": "None main()", "description": "Main function that generates the OpenAPI schema and writes it to 'interfaces/openapi.json'.", "scope": "", "scopeKind": ""}], "calls": ["src.api.main.app.openapi", "os.makedirs", "os.path.join", "json.dump"], "search-terms": ["generate_openapi", "OpenAPI schema", "FastAPI", "openapi.json", "schema generation", "interfaces"], "state": 2, "file_id": 2, "knowledge_revision": 28, "git_revision": "781c743fe8a5d882bffc8bf80864c46dfdd4ac87", "revision_history": [{"9": "781c743fe8a5d882bffc8bf80864c46dfdd4ac87"}, {"28": "781c743fe8a5d882bffc8bf80864c46dfdd4ac87"}], "ctags": [{"_type": "tag", "name": "main", "path": "/home/kavia/workspace/code-generation/dsp-devx-support-portal-97700-96769/backend/src/api/generate_openapi.py", "pattern": "/^def main() -> None:$/", "language": "Python", "typeref": "typename:None", "kind": "function", "signature": "()"}], "hash": "782cd6cce5fcbe368f12072a1d933135", "format-version": 4, "code-base-name": "backend", "filename": "backend/src/api/generate_openapi.py"}